cognite_robotics/__init__.py
cognite_robotics/config/config.py
cognite_robotics/data_classes.py
cognite_robotics/data_uploader/__init__.py
cognite_robotics/data_uploader/data_classes.py
cognite_robotics/data_uploader/data_uploader.py
cognite_robotics/data_uploader/data_uploader_task.py
cognite_robotics/data_uploader/helpers.py
cognite_robotics/grpc/clients/__init__.py
cognite_robotics/grpc/clients/robot_interface_client.py
cognite_robotics/grpc/clients/web_interface_client.py
cognite_robotics/grpc/helpers/__init__.py
cognite_robotics/grpc/helpers/bearer_token_auth.py
cognite_robotics/grpc/helpers/channel.py
cognite_robotics/grpc/helpers/messages.py
cognite_robotics/logging.py
cognite_robotics/metrics.py
cognite_robotics/protos/__init__.py
cognite_robotics/protos/messages/common_pb2.py
cognite_robotics/protos/messages/common_pb2.pyi
cognite_robotics/protos/messages/connectivity_pb2.py
cognite_robotics/protos/messages/connectivity_pb2.pyi
cognite_robotics/protos/messages/control_authority_pb2.py
cognite_robotics/protos/messages/control_authority_pb2.pyi
cognite_robotics/protos/messages/data_pb2.py
cognite_robotics/protos/messages/data_pb2.pyi
cognite_robotics/protos/messages/geometry_pb2.py
cognite_robotics/protos/messages/geometry_pb2.pyi
cognite_robotics/protos/messages/joint_state_pb2.py
cognite_robotics/protos/messages/joint_state_pb2.pyi
cognite_robotics/protos/messages/metrics_pb2.py
cognite_robotics/protos/messages/metrics_pb2.pyi
cognite_robotics/protos/messages/mission_event_pb2.py
cognite_robotics/protos/messages/mission_event_pb2.pyi
cognite_robotics/protos/messages/mission_log_pb2.py
cognite_robotics/protos/messages/mission_log_pb2.pyi
cognite_robotics/protos/messages/mission_pb2.py
cognite_robotics/protos/messages/mission_pb2.pyi
cognite_robotics/protos/messages/payloads_pb2.py
cognite_robotics/protos/messages/payloads_pb2.pyi
cognite_robotics/protos/messages/robot_control_pb2.py
cognite_robotics/protos/messages/robot_control_pb2.pyi
cognite_robotics_sdk-0.1.19.dist-info/METADATA
cognite_robotics_sdk-0.1.19.dist-info/WHEEL
cognite_robotics_sdk-0.1.19.dist-info/RECORD
