Metadata-Version: 2.1
Name: cognite-robotics-sdk
Version: 0.1.19
Summary: Cognite Robotics SDK
Author: Cognite Robotics
Author-email: robotics-team@cognite.com
Requires-Python: >=3.8,<4.0
Classifier: Programming Language :: Python :: 3
Classifier: Programming Language :: Python :: 3.8
Classifier: Programming Language :: Python :: 3.9
Classifier: Programming Language :: Python :: 3.10
Classifier: Programming Language :: Python :: 3.11
Requires-Dist: aiofiles (>=23.1.0,<24.0.0)
Requires-Dist: cognite-sdk (>=6.0.0,<7.0.0)
Requires-Dist: grpcio (>=1.58.0,<2.0.0)
Requires-Dist: prometheus-client (>=0.19.0,<0.20.0)
Requires-Dist: protobuf (>=4.23.0,<5.0.0)
Requires-Dist: pydantic (>=2.6.0,<2.7.0)
Requires-Dist: python-dotenv (>=0.21.1,<0.22.0)
Requires-Dist: tenacity (>=8.2.2,<9.0.0)
